pynq_cdma/__init__.py
pynq_cdma/cdma.py
pynq_cdma-0.1.0.dist-info/LICENSE
pynq_cdma-0.1.0.dist-info/METADATA
pynq_cdma-0.1.0.dist-info/WHEEL
pynq_cdma-0.1.0.dist-info/top_level.txt
pynq_cdma-0.1.0.dist-info/RECORD
