Metadata-Version: 2.1
Name: pynq-cdma
Version: 0.1.0
Summary: PYNQ Driver for Xilinx Central Direct Memory Access IP
Home-page: https://github.com/iamNCJ/PYNQ-CDMA-Driver
Author: NCJ
Author-email: me@ncj.wiki
License: UNKNOWN
Platform: UNKNOWN
Classifier: Programming Language :: Python :: 3
Classifier: License :: OSI Approved :: MIT License
Classifier: Operating System :: POSIX :: Linux
Requires-Python: >=3.6
License-File: LICENSE
Requires-Dist: pynq (>=2.6)
